feloopy/__init__.py
feloopy/_version.py
feloopy/cli.py
feloopy/feloopy.py
feloopy/agents/__init__.py
feloopy/agents/agent.py
feloopy/algorithms/__init__.py
feloopy/algorithms/constraint/__init__.py
feloopy/algorithms/exact/__init__.py
feloopy/algorithms/exact/benders.py
feloopy/algorithms/exact/multiobjective.py
feloopy/algorithms/heuristic/DE.py
feloopy/algorithms/heuristic/GA.py
feloopy/algorithms/heuristic/GWO.py
feloopy/algorithms/heuristic/SA.py
feloopy/algorithms/heuristic/TS.py
feloopy/algorithms/heuristic/__init__.py
feloopy/classes/__init__.py
feloopy/classes/constraint_programming.py
feloopy/classes/event_variable.py
feloopy/classes/event_variable_collection.py
feloopy/classes/linearization.py
feloopy/classes/multidim_variable.py
feloopy/classes/multidim_variable_collection.py
feloopy/classes/normal_constraint.py
feloopy/classes/special_constraint.py
feloopy/classes/tensor_variable.py
feloopy/classes/tensor_variable_collection.py
feloopy/clitools/__init__.py
feloopy/clitools/pkg_manager_detector.py
feloopy/clitools/utils.py
feloopy/generators/__init__.py
feloopy/generators/init_generator.py
feloopy/generators/model_generator.py
feloopy/generators/result_generator.py
feloopy/generators/solution_generator.py
feloopy/generators/variable_generator.py
feloopy/generators/init/__init__.py
feloopy/generators/init/casadi_init_generator.py
feloopy/generators/init/copt_init_generator.py
feloopy/generators/init/cplex_init_generator.py
feloopy/generators/init/gekko_init_generator.py
feloopy/generators/init/gurobi_init_generator.py
feloopy/generators/init/pulp_init_generator.py
feloopy/generators/init/pyomo_init_generator.py
feloopy/generators/model/__init__.py
feloopy/generators/model/casadi_model_generator.py
feloopy/generators/model/copt_model_generator.py
feloopy/generators/model/cplex_cp_model_generator.py
feloopy/generators/model/cplex_model_generator.py
feloopy/generators/model/cvxpy_model_generator.py
feloopy/generators/model/cylp_model_generator.py
feloopy-0.3.9.dist-info/licenses/license.txt
feloopy-0.3.9.dist-info/METADATA
feloopy-0.3.9.dist-info/WHEEL
feloopy-0.3.9.dist-info/entry_points.txt
feloopy-0.3.9.dist-info/top_level.txt
feloopy-0.3.9.dist-info/RECORD
