Metadata-Version: 2.4
Name: feloopy
Version: 0.3.9
Summary: FelooPy: Efficient and feature-rich integrated decision environment
Home-page: https://feloopy.github.io/
Download-URL: https://github.com/feloopy/feloopy/releases
Author: Keivan Tafakkori
Author-email: k.tafakkori@gmail.com
Maintainer: Keivan Tafakkori
Maintainer-email: k.tafakkori@gmail.com
License: MIT
Keywords: computer science,data science,decision making,decision science,industrial engineering,machine learning,management science,mathematical modeling,operations management,operations research,optimization,simulation,supply chain
Requires-Python: >=3.10
License-File: license.txt
Requires-Dist: gputil
Requires-Dist: infix
Requires-Dist: matplotlib
Requires-Dist: nbformat
Requires-Dist: numpy
Requires-Dist: openpyxl
Requires-Dist: pandas
Requires-Dist: psutil
Requires-Dist: py-cpuinfo
Requires-Dist: tabulate
Requires-Dist: win-unicode-console
Requires-Dist: xlsxwriter
Requires-Dist: tqdm
Requires-Dist: colorama
Requires-Dist: rich
Provides-Extra: pico
Provides-Extra: nano
Requires-Dist: pymprog==1.1.2; extra == "nano"
Requires-Dist: highspy==1.10.0; extra == "nano"
Provides-Extra: micro
Requires-Dist: pymprog==1.1.2; extra == "micro"
Requires-Dist: highspy==1.10.0; extra == "micro"
Requires-Dist: gekko==1.3.0; extra == "micro"
Requires-Dist: mealpy==3.0.1; extra == "micro"
Provides-Extra: mini
Requires-Dist: pymprog==1.1.2; extra == "mini"
Requires-Dist: highspy==1.10.0; extra == "mini"
Requires-Dist: gekko==1.3.0; extra == "mini"
Requires-Dist: mealpy==3.0.1; extra == "mini"
Requires-Dist: cvxpy==1.6.4; extra == "mini"
Requires-Dist: ortools==9.12.4544; extra == "mini"
Provides-Extra: full
Requires-Dist: pymprog==1.1.2; extra == "full"
Requires-Dist: highspy==1.10.0; extra == "full"
Requires-Dist: gekko==1.3.0; extra == "full"
Requires-Dist: mealpy==3.0.1; extra == "full"
Requires-Dist: cvxpy==1.6.4; extra == "full"
Requires-Dist: ortools==9.12.4544; extra == "full"
Requires-Dist: pydecision==4.7.5; extra == "full"
Requires-Dist: pymoo==0.6.1.3; extra == "full"
Requires-Dist: rsome==1.3.1; extra == "full"
Provides-Extra: stock
Requires-Dist: pymprog==1.1.2; extra == "stock"
Requires-Dist: highspy==1.10.0; extra == "stock"
Requires-Dist: gekko==1.3.0; extra == "stock"
Requires-Dist: mealpy==3.0.1; extra == "stock"
Requires-Dist: cvxpy==1.6.4; extra == "stock"
Requires-Dist: ortools==9.12.4544; extra == "stock"
Requires-Dist: pydecision==4.7.5; extra == "stock"
Requires-Dist: pymoo==0.6.1.3; extra == "stock"
Requires-Dist: rsome==1.3.1; extra == "stock"
Requires-Dist: linopy==0.5.2; extra == "stock"
Requires-Dist: mip==1.15.0; extra == "stock"
Requires-Dist: niapy==2.5.2; extra == "stock"
Requires-Dist: picos==2.6.0; extra == "stock"
Requires-Dist: pulp==3.1.1; extra == "stock"
Requires-Dist: pygad==3.4.0; extra == "stock"
Requires-Dist: pyomo==6.9.1; extra == "stock"
Requires-Dist: highsbox==1.10.0; extra == "stock"
Requires-Dist: pyoptinterface==0.4.1; extra == "stock"
Provides-Extra: hyper
Requires-Dist: pymprog==1.1.2; extra == "hyper"
Requires-Dist: highspy==1.10.0; extra == "hyper"
Requires-Dist: gekko==1.3.0; extra == "hyper"
Requires-Dist: mealpy==3.0.1; extra == "hyper"
Requires-Dist: cvxpy==1.6.4; extra == "hyper"
Requires-Dist: ortools==9.12.4544; extra == "hyper"
Requires-Dist: pydecision==4.7.5; extra == "hyper"
Requires-Dist: pymoo==0.6.1.3; extra == "hyper"
Requires-Dist: rsome==1.3.1; extra == "hyper"
Requires-Dist: linopy==0.5.2; extra == "hyper"
Requires-Dist: mip==1.15.0; extra == "hyper"
Requires-Dist: niapy==2.5.2; extra == "hyper"
Requires-Dist: picos==2.6.0; extra == "hyper"
Requires-Dist: pulp==3.1.1; extra == "hyper"
Requires-Dist: pygad==3.4.0; extra == "hyper"
Requires-Dist: pyomo==6.9.1; extra == "hyper"
Requires-Dist: highsbox==1.10.0; extra == "hyper"
Requires-Dist: pyoptinterface==0.4.1; extra == "hyper"
Requires-Dist: gurobipy==12.0.1; extra == "hyper"
Requires-Dist: cplex==22.1.2.0; extra == "hyper"
Requires-Dist: docplex==2.29.241; extra == "hyper"
Requires-Dist: xpress==9.5.4; extra == "hyper"
Requires-Dist: coptpy==7.2.6; extra == "hyper"
Requires-Dist: gamspy==1.8.0; extra == "hyper"
Provides-Extra: plus-gurobi
Requires-Dist: gurobipy==12.0.1; extra == "plus-gurobi"
Provides-Extra: plus-cplex
Requires-Dist: cplex==22.1.2.0; extra == "plus-cplex"
Requires-Dist: docplex==2.29.241; extra == "plus-cplex"
Provides-Extra: plus-xpress
Requires-Dist: xpress==9.5.4; extra == "plus-xpress"
Provides-Extra: plus-copt
Requires-Dist: coptpy==7.2.6; extra == "plus-copt"
Provides-Extra: plus-insideopt
Requires-Dist: insideopt-seeker==0.1.21; extra == "plus-insideopt"
Provides-Extra: plus-insideoptdemo
Requires-Dist: insideopt-demo==0.3.3; extra == "plus-insideoptdemo"
Provides-Extra: plus-gams
Requires-Dist: gamspy==1.8.0; extra == "plus-gams"
Provides-Extra: plus-jump
Requires-Dist: juliacall==0.9.24; extra == "plus-jump"
Provides-Extra: only-cylp
Requires-Dist: cylp==0.92.2; extra == "only-cylp"
Provides-Extra: only-linux
Requires-Dist: pymultiobjective==1.5.5; extra == "only-linux"
Provides-Extra: mega
Requires-Dist: pymprog==1.1.2; extra == "mega"
Requires-Dist: highspy==1.10.0; extra == "mega"
Requires-Dist: gekko==1.3.0; extra == "mega"
Requires-Dist: mealpy==3.0.1; extra == "mega"
Requires-Dist: cvxpy==1.6.4; extra == "mega"
Requires-Dist: ortools==9.12.4544; extra == "mega"
Requires-Dist: pydecision==4.7.5; extra == "mega"
Requires-Dist: pymoo==0.6.1.3; extra == "mega"
Requires-Dist: rsome==1.3.1; extra == "mega"
Requires-Dist: linopy==0.5.2; extra == "mega"
Requires-Dist: mip==1.15.0; extra == "mega"
Requires-Dist: niapy==2.5.2; extra == "mega"
Requires-Dist: picos==2.6.0; extra == "mega"
Requires-Dist: pulp==3.1.1; extra == "mega"
Requires-Dist: pygad==3.4.0; extra == "mega"
Requires-Dist: pyomo==6.9.1; extra == "mega"
Requires-Dist: highsbox==1.10.0; extra == "mega"
Requires-Dist: pyoptinterface==0.4.1; extra == "mega"
Requires-Dist: gurobipy==12.0.1; extra == "mega"
Requires-Dist: cplex==22.1.2.0; extra == "mega"
Requires-Dist: docplex==2.29.241; extra == "mega"
Requires-Dist: xpress==9.5.4; extra == "mega"
Requires-Dist: coptpy==7.2.6; extra == "mega"
Requires-Dist: gamspy==1.8.0; extra == "mega"
Requires-Dist: cylp==0.92.2; extra == "mega"
Requires-Dist: pymultiobjective==1.5.5; extra == "mega"
Provides-Extra: beta
Requires-Dist: casadi==3.7.0; extra == "beta"
Requires-Dist: scipy==1.15.2; extra == "beta"
Dynamic: author
Dynamic: author-email
Dynamic: description
Dynamic: description-content-type
Dynamic: download-url
Dynamic: home-page
Dynamic: keywords
Dynamic: license
Dynamic: license-file
Dynamic: maintainer
Dynamic: maintainer-email
Dynamic: provides-extra
Dynamic: requires-dist
Dynamic: requires-python
Dynamic: summary
